fxh_my_app/__init__.py
fxh_my_app/common.py
fxh_my_app/my_app.py
fxh_my_app-2.5.1.dist-info/WHEEL
fxh_my_app-2.5.1.dist-info/METADATA
fxh_my_app-2.5.1.dist-info/RECORD
