Metadata-Version: 2.1
Name: fxh-my-app
Version: 2.5.1
Summary: 
Author: juntao
Author-email: 61410813@qq.com
Requires-Python: >=3.8,<4.0
Classifier: Programming Language :: Python :: 3
Classifier: Programming Language :: Python :: 3.10
Classifier: Programming Language :: Python :: 3.8
Classifier: Programming Language :: Python :: 3.9
Requires-Dist: loguru (>=0.6.0,<0.7.0)
Requires-Dist: pymongo (>=4.1.1,<5.0.0)
Requires-Dist: redis (>=4.3.0,<5.0.0)
